[
        {
          "itemTitle": "Chocolate Covered",
          "itemDescription": "Test Description",
          "itemPrice": "1.99",
          "itemType": "macarons",
          "itemImageURL": "https://raw.githubusercontent.com/bzayats/tout_app_assets/master/assets/mock.api/images/details_screen/macarons/macaron_chocolate_covered.jpg",
          "productPairees": "Coffee, Sparling, Tea",
          "productLabels": "Almond Flour, Gluten Free, Let it Chill",
          "favorite": 0,
          "seasonalItem": "false"      
        },
        {          
          "itemTitle": "Vanilla Chocolate",
          "itemDescription": "Test Description 2",
          "itemPrice": "1.99",
          "itemType": "macarons",
          "itemImageURL": "https://raw.githubusercontent.com/bzayats/tout_app_assets/master/assets/mock.api/images/details_screen/macarons/macaron_vanilla_chocolate.jpg",
          "productPairees": "Coffee, Sparling, Tea",
          "productLabels": "Almond Flour, Gluten Free, Let it Chill",
          "favorite": 0,
          "seasonalItem": "true"       
        },
        {         
          "itemTitle": "Lemon",
          "itemDescription": "Test Description 3",
          "itemPrice": "1.99",
          "itemType": "macarons",
          "itemImageURL": "https://raw.githubusercontent.com/bzayats/tout_app_assets/master/assets/mock.api/images/details_screen/macarons/macaron_lemon.jpg",
          "productPairees": "Coffee, Sparling, Tea",
          "productLabels": "Almond Flour, Gluten Free, Let it Chill",
          "favorite": 0,
          "seasonalItem": "true"       
        },
        {
          "itemTitle": "Strawberry",
          "itemDescription": "Test Description 3",
          "itemPrice": "1.99",
          "itemType": "macarons",
          "itemImageURL": "https://raw.githubusercontent.com/bzayats/tout_app_assets/master/assets/mock.api/images/details_screen/macarons/macaron_strawberry.jpg",
          "productPairees": "Coffee, Sparling, Tea",
          "productLabels": "Almond Flour, Gluten Free, Let it Chill",
          "favorite": 0,
          "seasonalItem": "false"       
        },
        {
          "itemId": "5",
          "itemTitle": "Red Velvet",
          "itemDescription": "Test Description 4",
          "itemPrice": "1.99",
          "itemType": "macarons",
          "itemImageURL": "https://raw.githubusercontent.com/bzayats/tout_app_assets/master/assets/mock.api/images/details_screen/macarons/macaron_redvel.jpg",
          "productPairees": "Coffee, Sparling, Tea",
          "productLabels": "Almond Flour, Gluten Free, Let it Chill",
          "favorite": 0,
          "seasonalItem": "true"       
        },
        {
          "itemId": "6",
          "itemTitle": "Orange",
          "itemDescription": "Test Description 5",
          "itemPrice": "1.99",
          "itemType": "macarons",
          "itemImageURL": "https://raw.githubusercontent.com/bzayats/tout_app_assets/master/assets/mock.api/images/details_screen/macarons/macaron_orange.jpg",
          "productPairees": "Coffee, Sparling, Tea",
          "productLabels": "Almond Flour, Gluten Free, Let it Chill",
          "favorite": 0,
          "seasonalItem": "true"       
        },
        {
          "itemId": "7",
          "itemTitle": "Lime Basil",
          "itemDescription": "Test Description 6",
          "itemPrice": "1.99",
          "itemType": "macarons",
          "itemImageURL": "https://raw.githubusercontent.com/bzayats/tout_app_assets/master/assets/mock.api/images/details_screen/macarons/macaron_lime_basil.jpg",
          "productPairees": "Coffee, Sparling, Tea",
          "productLabels": "Almond Flour, Gluten Free, Let it Chill",
          "favorite": 0,
          "seasonalItem": "false"       
        },
        {
          "itemId": "8",
          "itemTitle": "Vanilla Bean",
          "itemDescription": "Test Description 7",
          "itemPrice": "1.99",
          "itemType": "macarons",
          "itemImageURL": "https://raw.githubusercontent.com/bzayats/tout_app_assets/master/assets/mock.api/images/details_screen/macarons/macaron_vanilla_bean.jpg",
          "productPairees": "Coffee, Sparling, Tea",
          "productLabels": "Almond Flour, Gluten Free, Let it Chill",
          "favorite": 0,
          "seasonalItem": "false"       
        },
        {
          "itemId": "9",
          "itemTitle": "Guava",
          "itemDescription": "Test Description 8",
          "itemPrice": "1.99",
          "itemType": "macarons",
          "itemImageURL": "https://raw.githubusercontent.com/bzayats/tout_app_assets/master/assets/mock.api/images/details_screen/macarons/macaron_guava.jpg",
          "productPairees": "Coffee, Sparling, Tea",
          "productLabels": "Almond Flour, Gluten Free, Let it Chill",
          "favorite": 0,
          "seasonalItem": "false"       
        }
]
      
